lauterbach/trace32/pystart/__init__.py
lauterbach/trace32/pystart/__version__.py
lauterbach/trace32/pystart/_connection.py
lauterbach/trace32/pystart/_exceptions.py
lauterbach/trace32/pystart/_interface.py
lauterbach/trace32/pystart/_powerview.py
lauterbach/trace32/pystart/py.typed
lauterbach_trace32_pystart-0.4.0.dist-info/LICENSE
lauterbach_trace32_pystart-0.4.0.dist-info/METADATA
lauterbach_trace32_pystart-0.4.0.dist-info/WHEEL
lauterbach_trace32_pystart-0.4.0.dist-info/top_level.txt
lauterbach_trace32_pystart-0.4.0.dist-info/RECORD
