Metadata-Version: 2.1
Name: lauterbach-trace32-pystart
Version: 0.4.0
Summary: start Lauterbach TRACE32
Home-page: https://www.lauterbach.com
Author: Lauterbach GmbH
Author-email: support@lauterbach.com
Maintainer: Lauterbach GmbH
Maintainer-email: support@lauterbach.com
License: MIT
Project-URL: Documentation, https://lauterbach-trace32-pystart.readthedocs.io
Project-URL: Repository, https://gitlab.com/lauterbach/pystart
Classifier: Programming Language :: Python :: 3
Classifier: Programming Language :: Python :: 3.7
Classifier: License :: OSI Approved :: MIT License
Classifier: Operating System :: OS Independent
Classifier: Topic :: Software Development :: Debuggers
Classifier: Intended Audience :: Developers
License-File: LICENSE
